smx/__init__.py
smx/memoize.py
smx/smx.py
smx/wsgi.py
smx-0.9.5.dist-info/entry_points.txt
smx-0.9.5.dist-info/LICENSE
smx-0.9.5.dist-info/WHEEL
smx-0.9.5.dist-info/METADATA
smx-0.9.5.dist-info/RECORD
