Metadata-Version: 2.1
Name: smx
Version: 0.9.5
Summary: Simple python macro expansion
Home-page: https://github.com/earonesty/python-smx
License: UNKNOWN
Author: Erik Aronesty
Author-email: erik@q32.com
Classifier: Intended Audience :: Developers
Classifier: License :: OSI Approved :: MIT License
Classifier: Programming Language :: Python
Classifier: Topic :: Software Development :: Libraries :: Python Modules
